djanticapi/__init__.py
djanticapi/authentication.py
djanticapi/exceptions.py
djanticapi/form.py
djanticapi/json.py
djanticapi/logger.py
djanticapi/permissions.py
djanticapi/response.py
djanticapi/utils.py
djanticapi/view.py
djanticapi/jwt/__init__.py
djanticapi/jwt/authentication.py
djanticapi/jwt/forms.py
djanticapi/jwt/views.py
djanticapi-0.0.6.dist-info/LICENSE
djanticapi-0.0.6.dist-info/WHEEL
djanticapi-0.0.6.dist-info/METADATA
djanticapi-0.0.6.dist-info/RECORD
