Metadata-Version: 2.1
Name: djanticapi
Version: 0.0.6
Summary: Pydantic data validation support for Django API View
Author: Bin Wen
Author-email: caowb@pillar-biosciences.com
Requires-Python: >=3.6
Classifier: License :: OSI Approved :: MIT License
Classifier: Operating System :: OS Independent
Classifier: Framework :: Django
Classifier: Framework :: Django :: 3.0
Classifier: Framework :: Django :: 3.1
Classifier: Framework :: Django :: 3.2
Classifier: Programming Language :: Python
Classifier: Programming Language :: Python :: 3.7
Classifier: Programming Language :: Python :: 3.8
Classifier: Programming Language :: Python :: 3.9
Requires-Dist: Django >=3.1.1
Requires-Dist: pydantic >=1.0.0,<2.0.0
Requires-Dist: orjson >=3.5.2
Requires-Dist: PyJWT>=1.5.2
